{"6.1.8": ["Jacob Perron", "jacob@openrobotics.org"], "6.1.7": ["Jacob Perron", "jacob@openrobotics.org"], "6.1.6": ["Jacob Perron", "jacob@openrobotics.org"], "6.1.5": ["Jacob Perron", "jacob@openrobotics.org"], "6.1.4": ["Jacob Perron", "jacob@openrobotics.org"], "6.1.3": ["Jacob Perron", "jacob@openrobotics.org"], "6.1.2": ["Jacob Perron", "jacob@openrobotics.org"], "6.1.1": ["Jacob Perron", "jacob@openrobotics.org"], "6.1.0": ["Jacob Perron", "jacob@openrobotics.org"], "6.0.0": ["Jacob Perron", "jacob@openrobotics.org"], "5.1.0": ["Jacob Perron", "jacob@openrobotics.org"], "5.0.0": ["Jacob Perron", "jacob@openrobotics.org"], "4.0.1": ["Jacob Perron", "jacob@openrobotics.org"], "4.0.0": ["Jacob Perron", "jacob@openrobotics.org"]}